LICENSE
README.md
setup.py
dfkv/__init__.py
dfkv/common.py
dfkv/dfkv.py
dfkv/dt.py
dfkv/ext.py
dfkv.egg-info/PKG-INFO
dfkv.egg-info/SOURCES.txt
dfkv.egg-info/dependency_links.txt
dfkv.egg-info/top_level.txt